mp4ansi/__init__.py
mp4ansi/mp4ansi.py
mp4ansi/statusline.py
mp4ansi/terminal.py
mp4ansi-0.4.2.dist-info/METADATA
mp4ansi-0.4.2.dist-info/WHEEL
mp4ansi-0.4.2.dist-info/namespace_packages.txt
mp4ansi-0.4.2.dist-info/top_level.txt
mp4ansi-0.4.2.dist-info/zip-safe
mp4ansi-0.4.2.dist-info/RECORD
