Metadata-Version: 2.1
Name: mp4ansi
Version: 0.4.2
Summary: A simple ANSI-based terminal emulator that provides multi-processing capabilities.
Home-page: https://github.com/soda480/mp4ansi
Author: Emilio Reyes
Author-email: soda480@gmail.com
Maintainer: 
Maintainer-email: 
License: Apache License, Version 2.0
Classifier: Development Status :: 4 - Beta
Classifier: Environment :: Console
Classifier: Environment :: Other Environment
Classifier: Intended Audience :: Developers
Classifier: Intended Audience :: System Administrators
Classifier: License :: OSI Approved :: Apache Software License
Classifier: Operating System :: POSIX :: Linux
Classifier: Programming Language :: Python
Classifier: Programming Language :: Python :: 3.6
Classifier: Programming Language :: Python :: 3.7
Classifier: Programming Language :: Python :: 3.8
Classifier: Programming Language :: Python :: 3.9
Classifier: Topic :: Software Development :: Libraries
Classifier: Topic :: Software Development :: Libraries :: Python Modules
Classifier: Topic :: System :: Networking
Classifier: Topic :: System :: Systems Administration
Requires-Dist: mpmq (==0.2.0)
Requires-Dist: cursor
Requires-Dist: colorama
Requires-Dist: progress1bar (==0.1.3)
